publicador/__init__.py
publicador/abstract.py
publicador/publicador.py
publicador/dropboxapi/__init__.py
publicador/dropboxapi/dropboxapi.py
publicador/googledrive/__init__.py
publicador/googledrive/googledrive.py
publicador-0.0.2.dist-info/LICENSE
publicador-0.0.2.dist-info/METADATA
publicador-0.0.2.dist-info/WHEEL
publicador-0.0.2.dist-info/top_level.txt
publicador-0.0.2.dist-info/RECORD
