Metadata-Version: 2.1
Name: publicador
Version: 0.0.2
Summary: Publicador de archivos en diferentes plataformas
Home-page: https://github.com/Cambalab/publicador
Author: José Luis Di Biase
Author-email: josx@camba.coop
License: UNKNOWN
Platform: UNKNOWN
Classifier: Programming Language :: Python :: 3
Classifier: License :: OSI Approved :: GNU General Public License v3 (GPLv3)
Classifier: Operating System :: OS Independent
Classifier: Topic :: Utilities
Requires-Python: >=3.6
Requires-Dist: dropbox
Requires-Dist: cd-drive
